colton_berry_project_3/__init__.py
colton_berry_project_3/client.py
colton_berry_project_3/core/__init__.py
colton_berry_project_3/core/api_error.py
colton_berry_project_3/core/client_wrapper.py
colton_berry_project_3/core/datetime_utils.py
colton_berry_project_3/core/file.py
colton_berry_project_3/core/force_multipart.py
colton_berry_project_3/core/http_client.py
colton_berry_project_3/core/http_response.py
colton_berry_project_3/core/http_sse/__init__.py
colton_berry_project_3/core/http_sse/_api.py
colton_berry_project_3/core/http_sse/_decoders.py
colton_berry_project_3/core/http_sse/_exceptions.py
colton_berry_project_3/core/http_sse/_models.py
colton_berry_project_3/core/jsonable_encoder.py
colton_berry_project_3/core/pydantic_utilities.py
colton_berry_project_3/core/query_encoder.py
colton_berry_project_3/core/remove_none_from_dict.py
colton_berry_project_3/core/request_options.py
colton_berry_project_3/core/serialization.py
colton_berry_project_3/environment.py
colton_berry_project_3/errors/__init__.py
colton_berry_project_3/errors/bad_request_error.py
colton_berry_project_3/errors/method_not_allowed_error.py
colton_berry_project_3/errors/not_found_error.py
colton_berry_project_3/plant/__init__.py
colton_berry_project_3/plant/client.py
colton_berry_project_3/plant/raw_client.py
colton_berry_project_3/plant/types/__init__.py
colton_berry_project_3/plant/types/search_plants_by_status_request_status.py
colton_berry_project_3/py.typed
colton_berry_project_3/types/__init__.py
colton_berry_project_3/types/api_version_enum.py
colton_berry_project_3/types/plant.py
colton_berry_project_3/types/plant_messages_item.py
colton_berry_project_3/types/plant_response.py
colton_berry_project_3/types/plant_status.py
colton_berry_project_3/types/tool_message_complete.py
colton_berry_project_3/types/tool_message_delayed.py
colton_berry_project_3/types/tool_message_failed.py
colton_berry_project_3/types/tool_message_start.py
colton_berry_project_3/types/user.py
colton_python-0.0.1.dist-info/METADATA
colton_python-0.0.1.dist-info/WHEEL
colton_python-0.0.1.dist-info/RECORD
